Workbook

Sheet Instructions
A1: INSTRUCTIONS — MIST BLITZ FS MASTER WORKBOOK
A2: Read this first. Vehicle Dynamics owns the model; every team pulls from it. Companion to the VD Handbook (Books One–Five).
A4: 1. WHAT THIS WORKBOOK IS
A5: A single source of truth for the car's numbers. The Vehicle Dynamics team owns the Master sheet. A component Mass Budget and a Tyre model feed Master automatically; VD calculation sheets turn those into loads, spring rates, load cases and lap-sim inputs; and every other sub-team has a hand-off sheet that pulls what it needs live and feeds its results back. Change one number and the whole model updates.
A6: 2. THE GOLDEN RULE
A7: No team keeps a private copy of a shared number. If it is on Master, read it from Master. If you measure something that belongs on Master (a real mass, a tested stiffness, an aero coefficient), put it in your sheet's 'give back' section and tell VD, who updates the model. Log any change to a frozen number in the ChangeLog.
A8: 3. CELL COLOUR LEGEND
A9: Blue on yellow | B9: Typed INPUT — you may edit this cell.
A10: Green text | B10: LINK — pulled from another sheet. Do not type over it.
A11: Black text | B11: COMPUTED here by a formula. Do not type over it.
A12: 4. HOW DATA FLOWS
A13: MassBudget + Tyre → Master → LoadTransfer / Springs / LoadCases / LapSim → team hand-off sheets (Chassis, Powertrain, Aero, Brakes, Telemetry, ECS) → Dashboard & Figures summarise it. The teams' 'give back' values flow back into MassBudget and Master.
A14: 5. TAB-BY-TAB GUIDE
A15: Dashboard | B15: Live KPI tiles + g–g and corner-load charts. The one-glance view.
A16: Figures | B16: EDR-ready charts (tyre curve, mass breakdown, g–g). Copy into the report.
A17: Master | B17: The car's canonical numbers. VD-owned. Edit blue inputs only.
A18: MassBudget | B18: Component masses + positions → total mass, CoG, yaw inertia. Every team updates its own parts.
A19: Tyre | B19: Chosen tyre + Magic-Formula operating values. Replace placeholders with the fitted model.
A20: LoadTransfer / Springs / LoadCases / LapSim | B20: VD calculations — loads, rates, FEA cases, sim inputs. Formula-driven.
A21: Chassis / Powertrain / Aero / Brakes / Ergonomics / Telemetry / ECS | B21: Per-team hand-offs: pull from Master, give results back.
A22: DecisionMatrix | B22: Weighted (Pugh) selection template for any design choice.
A23: Targets | B23: Target vs achieved tracker — the validation story for the EDR.
A24: Validation | B24: Measured vs predicted + % error — model correlation.
A25: Nomenclature / Units | B25: Symbol list and unit conversions for the EDR.
A26: Setup / TestLog / Procurement / Gates / ChangeLog | B26: Operational trackers.
A27: 6. USING IT DURING THE EDR
A28: Figures: paste the live charts straight in. Nomenclature: your symbol table. DecisionMatrix: justify every selection. Targets & Validation: the design-verification narrative judges reward. MassBudget: the mass table. LoadCases: the structural inputs. Keep the numbers in the report identical to the workbook — one source of truth means the EDR and the car never disagree.
A29: 7. SHARING ON ONEDRIVE
A30: Upload the .xlsx to OneDrive/SharePoint and share with edit rights for co-authoring in Excel on the web — multiple teams can work at once and all formulas/links keep working. Decide one VD owner for the Master sheet so inputs are not overwritten. Keep ONE master copy; do not email around forks (that breaks the single-source-of-truth rule).
A31: 7b. GOOGLE SHEETS & LINKED TEAM FILES (recommended for this team)
A32: Drag this .xlsx into Google Drive and open with Google Sheets — all formulas, links and charts convert. In Google Sheets, cross-file live links actually work, so each team keeps its OWN working file and pulls the shared numbers from this master with IMPORTRANGE. In a team file: =IMPORTRANGE("<master-sheet-URL>","Master!C8"). The first time, click the cell and press 'Allow access' to connect the two files (one-time, per pair of files — no add-on needed). The starter team files already contain these formulas with a cell to paste the master URL into.
A33: Keep this master as the ONE source of truth; teams pull from it and push their results back into their hand-off tab here. No paid add-ons are required. For one-click 'export this section as an image/PDF' buttons in Google Sheets, use Apps Script (Extensions → Apps Script — free, built in); the Excel VBA above does not run in Google Sheets.
A34: 8. EXPORTING SECTIONS AS PICTURES / PDF
A35: Print areas are set so each report sheet exports cleanly. To share a table as an image: (a) select the range, Home → Copy → Copy as Picture, paste into the EDR/chat; or (b) File → Export → PDF (or Print → Save as PDF) for the active sheet; or (c) on Excel web, use the sheet's '...' → Print to PDF. Charts copy as pictures directly (right-click → Copy).
A36: 9. OPTIONAL MACROS (desktop Excel only — not Excel web)
A37: Excel on the web does not run macros, so the workbook is kept as .xlsx for universal use. If you want one-click export on desktop Excel, save a copy as .xlsm, press Alt+F11, insert a Module and paste the two macros below, then add buttons (Developer → Insert → Button) linked to them.
A38: Sub ExportActiveSheetPDF()
... A57: Owner: Vehicle Dynamics team. Author: Tahmid Muntasir Auhin, Team Captain, MIST Blitz 2024–2026. Companion to the VD Handbook, Books One–Five.

Sheet Dashboard
A1: DASHBOARD — the car at a glance
A2: Live snapshot — every tile and chart updates when an input changes anywhere in the model.
B4: Total mass (kg) | E4: Front mass | H4: CoG height (mm) | K4: Yaw inertia (kg·m²)
B5: =Master!C9 -> 264 | E5: =Master!C10 -> 0.45686706 | H5: =Master!C11 -> 263.40909 | K5: =Master!C12 -> 53.384439
B8: Target lateral (g) | E8: Skidpad V (m/s) | H8: Front spring (N/mm) | K8: Rear spring (N/mm)
B9: =Master!C25 -> 1.5 | E9: =SQRT(Master!C25*9.81*7.625) -> 10.592539 | H9: =Springs!B7 -> 30.512996 | K9: =Springs!C7 -> 43.284615
B12: Brake bias (front) | E12: Roll gradient (deg/g)
B13: =Brakes!B8 -> 0.71177908 | E13: =Master!C27 -> 1.5
B34: TEAM DATA PICKUP — each team: here are your live numbers from VD, and the tab with your full hand-off
B35: CHASSIS | H35: POWERTRAIN & DRIVETRAIN
B36: Total mass target (kg) | E36: =Master!C9 -> 264 | H36: Rear axle load (N) | K36: =Master!C35 -> 1406.6274
B37: CoG height (mm) | E37: =Master!C11 -> 263.40909 | H37: Rear load under accel (N) | K37: =Master!C35+LoadTransfer!C8 -> 2066.8088
B38: Wheelbase (mm) | E38: =Master!C15 -> 1550 | H38: Peak μ (traction) | K38: =Master!C20 -> 1.5
B39: Design load — max lateral (N) | E39: =LoadCases!F5 -> 1454.2561 | H39: Rolling radius (mm) | K39: =Master!C23 -> 228
B40: Full hand-off → 'Chassis' tab | H40: Full hand-off → 'Powertrain' tab
B42: AERO & COOLING | H42: BRAKING
B43: Total mass (kg) | E43: =Master!C9 -> 264 | H43: Front axle braking (N) | K43: =LoadTransfer!C15 -> 1843.3939
B44: CoG height (mm) | E44: =Master!C11 -> 263.40909 | H44: Rear axle braking (N) | K44: =LoadTransfer!C16 -> 746.44606
B45: Ride height (mm) | E45: =Master!C18 -> 40 | H45: Ideal front bias | K45: =(Master!C34+LoadTransfer!C8)/Master!C33 -> 0.71177908
B46: Target lateral (g) | E46: =Master!C25 -> 1.5 | H46: Target decel (g) | K46: =Master!C26 -> 1.5
B47: Full hand-off → 'Aero' tab | H47: Full hand-off → 'Brakes' tab
B49: ERGONOMICS | H49: DAQ · TELEMETRY / ELECTRONICS
B50: Wheelbase (mm) | E50: =Master!C15 -> 1550 | H50: Target lateral (g) | K50: =Master!C25 -> 1.5
B51: Total mass (kg) | E51: =Master!C9 -> 264 | H51: Total mass (kg) | K51: =Master!C9 -> 264
B52: CoG height (mm) | E52: =Master!C11 -> 263.40909 | H52: Yaw inertia (kg·m²) | K52: =Master!C12 -> 53.384439
B53: Full hand-off → 'Ergonomics' tab | H53: Full hand-off → 'Telemetry' tab

Sheet Figures
A1: FIGURES — EDR-ready charts
A2: These update live from the model — copy straight into the EDR. Replace the placeholder tyre values on the Tyre sheet with your fitted Magic Formula for a defensible lateral-force figure.
B22: Fig A. Tyre lateral force vs slip angle (simplified Magic Formula from Master μ, Cα). | K22: Fig B. Mass breakdown by component (from MassBudget).
B42: Fig C. Per-corner vertical load at the grip limit. | K42: Fig D. g–g envelope (friction circle) at target grip.

Sheet Master
A1: MASTER — CAR PARAMETER SHEET (single source of truth)
A2: The VD team owns this sheet. GREEN cells pull from MassBudget/Tyre automatically; BLUE/yellow cells are typed inputs; BLACK cells are computed here. Every other team reads from here — do not keep private copies of these numbers.
A4: Parameter | B4: Symbol | C4: Value | D4: Unit | E4: Source | F4: Confidence | G4: Owner | H4: Updated | I4: Notes
A5: IDENTITY
A6: Car / season | B6: — | C6: Blitz — 2026 | D6: — | E6: — | F6: — | G6: VD | H6: 2026-10-08
A7: Competition | B7: — | C7: FS Combustion | D7: — | E7: — | F7: — | G7: VD | H7: 2026-10-08
A8: MASS & INERTIA
A9: Total mass (with driver) | B9: m | C9: =MassBudget!B28 -> 264 | D9: kg | E9: MassBudget | F9: Live | G9: VD | H9: 2026-10-08
A10: Front mass fraction | B10: — | C10: =MassBudget!B33 -> 0.45686706 | D10: - | E10: MassBudget | F10: Live | G10: VD | H10: 2026-10-08
A11: CoG height | B11: h | C11: =MassBudget!B31 -> 263.40909 | D11: mm | E11: MassBudget | F11: Est | G11: VD | H11: 2026-10-08
A12: Yaw inertia | B12: Izz | C12: =MassBudget!B32 -> 53.384439 | D12: kg·m² | E12: MassBudget | F12: Est | G12: VD | H12: 2026-10-08
A13: Unsprung mass per corner | B13: mu | C13: 12 | D13: kg | E13: CAD | F13: Est | G13: VD | H13: 2026-10-08
A14: GEOMETRY
A15: Wheelbase | B15: L | C15: 1550 | D15: mm | E15: Design | F15: Frozen@G2 | G15: VD | H15: 2026-10-08
A16: Front track | B16: tf | C16: 1200 | D16: mm | E16: Design | F16: Frozen@G2 | G16: VD | H16: 2026-10-08
A17: Rear track | B17: tr | C17: 1180 | D17: mm | E17: Design | F17: Frozen@G2 | G17: VD | H17: 2026-10-08
A18: Ride height | B18: — | C18: 40 | D18: mm | E18: Design | F18: — | G18: VD | H18: 2026-10-08
A19: TYRE (from Tyre sheet)
A20: Peak lateral μ | B20: μy | C20: =Tyre!C7 -> 1.5 | D20: - | E20: Tyre | F20: — | G20: VD | H20: 2026-10-08
A21: Cornering stiffness | B21: Cα | C21: =Tyre!C8 -> 1100 | D21: N/deg | E21: Tyre | F21: — | G21: VD | H21: 2026-10-08
A22: Peak slip angle | B22: αp | C22: =Tyre!C9 -> 7 | D22: deg | E22: Tyre | F22: — | G22: VD | H22: 2026-10-08
A23: Loaded rolling radius | B23: Re | C23: =Tyre!C15 -> 228 | D23: mm | E23: Tyre | F23: — | G23: VD | H23: 2026-10-08
A24: TARGETS
A25: Target lateral accel | B25: ay | C25: 1.5 | D25: g | E25: Lap sim | F25: — | G25: VD | H25: 2026-10-08
A26: Target braking decel | B26: ax | C26: 1.5 | D26: g | E26: Brake calc | F26: — | G26: Braking | H26: 2026-10-08
A27: Roll gradient target | B27: — | C27: 1.5 | D27: deg/g | E27: VD | F27: — | G27: VD | H27: 2026-10-08
A28: Ride frequency front | B28: ff | C28: 2.8 | D28: Hz | E28: VD | F28: — | G28: VD | H28: 2026-10-08
A29: Ride frequency rear | B29: fr | C29: 3 | D29: Hz | E29: VD | F29: — | G29: VD | H29: 2026-10-08
A30: TLLTD (front share) | B30: — | C30: 0.52 | D30: - | E30: VD | F30: — | G30: VD | H30: 2026-10-08
A31: Motion ratio (wheel→spring) | B31: MR | C31: 0.7 | D31: - | E31: VD | F31: Verify on car | G31: VD | H31: 2026-10-08
A32: DERIVED (computed here)
A33: Weight | B33: W | C33: =C9*9.81 -> 2589.84 | D33: N | E33: m×g | F33: Live | G33: VD | H33: 2026-10-08
A34: Front axle static load | B34: Wf | C34: =C33*C10 -> 1183.2126 | D34: N | E34: calc | F34: Live | G34: VD | H34: 2026-10-08
A35: Rear axle static load | B35: Wr | C35: =C33*(1-C10) -> 1406.6274 | D35: N | E35: calc | F35: Live | G35: VD | H35: 2026-10-08
A36: Avg track | B36: t | C36: =(C16+C17)/2 -> 1190 | D36: mm | E36: calc | F36: Live | G36: VD | H36: 2026-10-08

Sheet MassBudget
A1: MASS BUDGET — live component list (VD-owned)
A2: Fill blue/yellow cells. Totals + CoG + yaw inertia compute automatically and feed the Master sheet. x = aft of front axle, y = +left of centreline, z = height above ground.
A4: Component | B4: Mass (kg) | C4: x from front axle (mm) | D4: y from CL (mm) | E4: z height (mm) | F4: Status | G4: Owner | H4: Notes
A5: Engine + fluids | B5: 38 | C5: 1250 | D5: 0 | E5: 260 | F5: CAD | G5: Powertrain
A6: Chassis + mounts | B6: 34 | C6: 780 | D6: 0 | E6: 250 | F6: CAD | G6: Chassis
A7: Driver (strapped) | B7: 75 | C7: 560 | D7: 0 | E7: 300 | F7: Rules | G7: VD
A8: Differential + chain | B8: 9 | C8: 1420 | D8: 0 | E8: 230 | F8: CAD | G8: Powertrain
A9: Axles + CV joints | B9: 6 | C9: 1500 | D9: 0 | E9: 220 | F9: CAD | G9: Powertrain
A10: Fuel (half tank) | B10: 4 | C10: 1150 | D10: 0 | E10: 260 | F10: Est | G10: Powertrain
A11: Cooling (radiator+fluid) | B11: 6 | C11: 1480 | D11: -200 | E11: 340 | F11: CAD | G11: Aero&Cooling
A12: Front suspension (x2) | B12: 14 | C12: 0 | D12: 0 | E12: 230 | F12: CAD | G12: VD
A13: Rear suspension (x2) | B13: 15 | C13: 1550 | D13: 0 | E13: 230 | F13: CAD | G13: VD
A14: Wheels + tyres (front x2) | B14: 10 | C14: 0 | D14: 0 | E14: 230 | F14: Supplier | G14: VD
A15: Wheels + tyres (rear x2) | B15: 11 | C15: 1550 | D15: 0 | E15: 230 | F15: Supplier | G15: VD
A16: Bodywork + undertray | B16: 12 | C16: 900 | D16: 0 | E16: 180 | F16: CAD | G16: Aero&Cooling
... A22: DAQ + sensors | B22: 3 | C22: 820 | D22: 0 | E22: 330 | F22: CAD | G22: Telemetry
A27: COMPUTED (feeds Master — do not type over)
A28: Total mass (with driver) | B28: =SUM(B5:B25) -> 264 | C28: kg
A29: x_cg from front axle | B29: =SUMPRODUCT(B5:B25,C5:C25)/SUM(B5:B25) -> 841.85606 | C29: mm
A30: y_cg from centreline | B30: =SUMPRODUCT(B5:B25,D5:D25)/SUM(B5:B25) -> -0.75757576 | C30: mm
A31: CoG height (z_cg) | B31: =SUMPRODUCT(B5:B25,E5:E25)/SUM(B5:B25) -> 263.40909 | C31: mm
A32: Yaw inertia Izz (estimate) | B32: =SUMPRODUCT(B5:B25,((C5:C25-B29)/1000)^2+((D5:D25-B30)/1000)^2) -> 53.384439 | C32: kg·m²
A33: Front mass fraction | B33: =1-(B29/Master!C15) -> 0.45686706 | C33: -

Sheet Tyre
A1: TYRE MODEL — chosen tyre & operating values (VD-owned)
A2: From the TTC Magic-Formula fit (Book One). Until fitted, use placeholder values and mark Confidence = Placeholder. Feeds Master, LapSim and LoadCases.
A4: Parameter | B4: Symbol | C4: Value | D4: Unit | E4: Source / Confidence | F4: Notes
A5: Tyre size | B5: — | C5: 18×7.7-10 | D5: — | E5: Chosen
A6: Compound | B6: — | C6: — | D6: — | E6: Chosen
A7: Peak lateral μ (track-scaled) | B7: μy | C7: 1.5 | D7: — | E7: Placeholder
A8: Cornering stiffness (op. load) | B8: Cα | C8: 1100 | D8: N/deg | E8: Placeholder
A9: Peak slip angle | B9: αp | C9: 7 | D9: deg | E9: Placeholder
A10: Load sensitivity | B10: ∂μ/∂Fz | C10: 0.15 | D10: /kN | E10: Placeholder
A11: Baseline pressure (hot) | B11: P | C11: 83 | D11: kPa | E11: Placeholder
A12: Static camber front | B12: γf | C12: -2 | D12: deg | E12: Baseline
A13: Static camber rear | B13: γr | C13: -1.5 | D13: deg | E13: Baseline
A14: Friction scaling factor | B14: λμ | C14: 0.65 | D14: — | E14: Assumed
A15: Loaded rolling radius | B15: Re | C15: 228 | D15: mm | E15: CAD/Supplier

Sheet LoadTransfer
A1: LOAD TRANSFER & BALANCE (VD calc)
A2: All values pull from Master and recompute automatically. Simplified setup-level model: lateral transfer split front/rear by TLLTD; braking transfer about the wheelbase. Feeds LoadCases, Brakes and Powertrain.
A4: Quantity | B4: Symbol | C4: Value | D4: Unit | E4: Formula / assumption
A5: Total lateral load transfer | B5: ΔWt | C5: =Master!C9*Master!C25*9.81*Master!C11/Master!C36 -> 859.90008 | D5: N | E5: m·ay·h/t (h,t in m cancels mm)
A6: Front axle lateral transfer | B6: ΔWf | C6: =Master!C30*C5 -> 447.14804 | D6: N | E6: TLLTD_front × total
A7: Rear axle lateral transfer | B7: ΔWr | C7: =(1-Master!C30)*C5 -> 412.75204 | D7: N | E7: (1-TLLTD) × total
A8: Longitudinal transfer (braking) | B8: ΔWx | C8: =Master!C9*Master!C26*9.81*Master!C11/Master!C15 -> 660.18135 | D8: N | E8: m·ax·h/L
A9: PER-CORNER VERTICAL LOAD AT THE LIMIT (N)
A10: Corner | C10: Load (N) | E10: Formula
A11: Outer front | C11: =Master!C34/2+C6 -> 1038.7543 | E11: static front/2 + front transfer
A12: Inner front | C12: =Master!C34/2-C6 -> 144.45825 | E12: static front/2 - front transfer
A13: Outer rear | C13: =Master!C35/2+C7 -> 1116.0658 | E13: static rear/2 + rear transfer
A14: Inner rear | C14: =Master!C35/2-C7 -> 290.56167 | E14: static rear/2 - rear transfer
A15: Front axle under braking | C15: =Master!C34+C8 -> 1843.3939 | E15: static front + long transfer
A16: Rear axle under braking | C16: =Master!C35-C8 -> 746.44606 | E16: static rear - long transfer

Sheet Springs
A1: SPRINGS, ROLL & DAMPERS (VD calc)
A2: Ride-frequency method. Sprung corner mass from Master; wheel rate and spring rate computed through the motion ratio. Order the nearest available spring and re-check the frequency.
A4: Quantity | B4: Front | C4: Rear | D4: Unit | E4: Formula / note
A5: Sprung corner mass | B5: =Master!C9*Master!C10/2-Master!C13 -> 48.306452 | C5: =Master!C9*(1-Master!C10)/2-Master!C13 -> 59.693548 | D5: kg | E5: axle mass /2 − unsprung corner
A6: Wheel rate | B6: =(2*PI()*Master!C28)^2*B5/1000 -> 14.951368 | C6: =(2*PI()*Master!C29)^2*C5/1000 -> 21.209461 | D6: N/mm | E6: (2πf)²·m
A7: Spring rate (through MR) | B7: =B6/Master!C31^2 -> 30.512996 | C7: =C6/Master!C31^2 -> 43.284615 | D7: N/mm | E7: wheel rate / MR² — pick nearest available
A9: ROLL (estimate — fill the two inputs)
A10: Sprung weight | B10: =Master!C9*0.88*9.81 -> 2279.0592 | D10: N
A11: Sprung CoG above roll axis (H) | B11: 250 | D11: mm
A12: Required total roll stiffness | B12: =B10*(B11/1000)/Master!C27*57.3/57.3 -> 379.8432 | D12: N·m/deg

Sheet LoadCases
A1: STRUCTURAL LOAD CASES (VD → Chassis / Structures)
A2: Peak tyre forces for FEA, built from the tyre μ and the per-corner loads in LoadTransfer. Enter a dynamic magnification factor (DMF) per case; the design load is the base load × DMF.
A4: Load case | B4: Vertical Fz (N) | C4: Lateral Fy (N) | D4: Longitudinal Fx (N) | E4: DMF | F4: Design Fz (N)
A5: Max lateral (outer front) | B5: =LoadTransfer!C11 -> 1038.7543 | C5: =Master!C20*LoadTransfer!C11 -> 1558.1315 | D5: 0 | E5: 1.4 | F5: =B5*E5 -> 1454.2561
A6: Max lateral (outer rear) | B6: =LoadTransfer!C13 -> 1116.0658 | C6: =Master!C20*LoadTransfer!C13 -> 1674.0986 | D6: 0 | E6: 1.4 | F6: =B6*E6 -> 1562.4921
A7: Max braking (front axle) | B7: =LoadTransfer!C15 -> 1843.3939 | C7: 0 | D7: =Master!C20*LoadTransfer!C15 -> 2765.0909 | E7: 1.4 | F7: =B7*E7 -> 2580.7515
A8: Combined (outer front) | B8: =LoadTransfer!C11 -> 1038.7543 | C8: =0.7*Master!C20*LoadTransfer!C11 -> 1090.6921 | D8: =0.7*Master!C20*LoadTransfer!C11 -> 1090.6921 | E8: 1.5 | F8: =B8*E8 -> 1558.1315
A9: Bump / kerb strike (per corner) | B9: =3*Master!C34/2 -> 1774.8189 | C9: 0 | D9: 0 | E9: 2.5 | F9: =B9*E9 -> 4437.0472
A11: FEA targets: FoS ≥ 1.5 on yield (ductile), buckling FoS ≥ 2–3 on struts, and check stiffness (upright camber-compliance < ~0.1–0.2° at max lateral).

Sheet LapSim
A1: LAP-SIM INPUTS (VD → everyone)
A2: Everything the lap simulation needs, in one place, pulling from Master, Tyre and Aero. Keep the sim reading from here so it never drifts from the car.
A4: Parameter | B4: Value | C4: Unit | D4: Source
A5: Total mass | B5: =Master!C9 -> 264 | C5: kg | D5: Master
A6: Front mass fraction | B6: =Master!C10 -> 0.45686706 | C6: - | D6: Master
A7: CoG height | B7: =Master!C11 -> 263.40909 | C7: mm | D7: Master
A8: Wheelbase | B8: =Master!C15 -> 1550 | C8: mm | D8: Master
A9: Front / rear track | B9: =Master!C16 -> 1200 | C9: mm | D9: Master
A10: Peak lateral μ | B10: =Master!C20 -> 1.5 | C10: - | D10: Tyre
A11: Cornering stiffness | B11: =Master!C21 -> 1100 | C11: N/deg | D11: Tyre
A12: Loaded rolling radius | B12: =Master!C23 -> 228 | C12: mm | D12: Tyre
A13: Downforce coeff (Cl·A) | B13: =Aero!C8 -> kg | C13: m² | D13: Aero
A14: Drag coeff (Cd·A) | B14: =Aero!C9 -> g | C14: m² | D14: Aero
A15: Engine peak power | B15: =Powertrain!C8 -> N | C15: kW | D15: Powertrain
A16: Final drive ratio | B16: =Powertrain!C10 -> N | C16: - | D16: Powertrain
A18: Skidpad check: V = | B18: =SQRT(Master!C25*9.81*7.625) -> 10.592539 | C18: m/s

Sheet Chassis
A1: CHASSIS — hand-off from VD
A2: Mass target, load cases and hardpoints come from VD. Return the as-built mass and measured stiffness.
A4: WHAT VD GIVES YOU (pulled live — do not edit)
A5: Parameter | B5: Value | C5: Unit | D5: Source
A6: Total mass target | B6: =Master!C9 -> 264 | C6: kg | D6: Master
A7: CoG height | B7: =Master!C11 -> 263.40909 | C7: mm | D7: Master
A8: Wheelbase | B8: =Master!C15 -> 1550 | C8: mm | D8: Master
A9: Front / rear track | B9: =Master!C16 -> 1200 | C9: mm | D9: Master
A10: Design load (max lateral) | B10: =LoadCases!F5 -> 1454.2561 | C10: N | D10: LoadCases
A11: Design load (combined) | B11: =LoadCases!F8 -> 1558.1315 | C11: N | D11: LoadCases
A13: WHAT YOU GIVE BACK TO VD (fill these — they feed the model)
A14: Parameter | B14: Value | C14: Unit | D14: Notes
A15: Chassis mass (as built) | B15: 34 | C15: kg | D15: Feeds the mass budget row — update MassBudget.
A16: Torsional stiffness target | B16: 1600 | C16: N·m/deg | D16: Usually set a few × total roll stiffness.
A17: Torsional stiffness (measured) | C17: N·m/deg | D17: From the twist test.
A18: First structural mode | C18: Hz | D18: Keep above engine excitation.
A20: Hardpoints are frozen by VD at Gate G3 and live in the kinematics file; copy the pickup coordinates here if the chassis team prefers them in one place.

Sheet Powertrain
A1: POWERTRAIN & DRIVETRAIN — hand-off
A2: Mass, loads and the traction limit come from VD. Return the engine and driveline numbers the lap sim needs.
A4: WHAT VD GIVES YOU (pulled live — do not edit)
A5: Parameter | B5: Value | C5: Unit | D5: Source
A6: Total mass | B6: =Master!C9 -> 264 | C6: kg | D6: Master
A7: Rear axle static load | B7: =Master!C35 -> 1406.6274 | C7: N | D7: Master
A8: Rear axle load under accel | B8: =Master!C35+LoadTransfer!C8 -> 2066.8088 | C8: N | D8: LoadTransfer
A9: Peak μ (for traction limit) | B9: =Master!C20 -> 1.5 | C9: - | D9: Tyre
A10: Traction-limited rear force | B10: =Master!C20*(Master!C35+LoadTransfer!C8) -> 3100.2132 | C10: N | D10: μ × rear dynamic load
A11: Loaded rolling radius | B11: =Master!C23 -> 228 | C11: mm | D11: Tyre
A13: WHAT YOU GIVE BACK TO VD (fill these — they feed the model)
A14: Parameter | B14: Value | C14: Unit | D14: Notes
A15: Engine peak power | B15: 32 | C15: kW | D15: Lap sim input.
A16: Engine peak torque | B16: 35.3 | C16: N·m
A17: Final drive ratio | B17: 3 | C17: - | D17: Lap sim input.
A18: Diff type / ramps | B18: Salisbury LSD | C18: - | D18: Entry/exit balance tool.
A19: Max torque per wheel | C19: N·m | D19: Compare to traction-limited × Re.

Sheet Aero
A1: AERO & COOLING — hand-off
A2: Platform and target numbers come from VD; return the aero map so the lap sim and balance are correct at speed.
A4: WHAT VD GIVES YOU (pulled live — do not edit)
A5: Parameter | B5: Value | C5: Unit | D5: Source
A6: Ride height | B6: =Master!C18 -> 40 | C6: mm | D6: Master
A7: CoG height | B7: =Master!C11 -> 263.40909 | C7: mm | D7: Master
A8: Total mass | B8: =Master!C9 -> 264 | C8: kg | D8: Master
A9: Target lateral accel | B9: =Master!C25 -> 1.5 | C9: g | D9: Master
A11: WHAT YOU GIVE BACK TO VD (fill these — they feed the model)
A12: Parameter | B12: Value | C12: Unit | D12: Notes
A13: Cl·A (downforce coeff) | B13: 0 | C13: m² | D13: Lap sim input (LapSim reads C8).
A14: Cd·A (drag coeff) | B14: 0 | C14: m² | D14: Lap sim input (LapSim reads C9).
A15: Aero balance (front share) | B15: 0 | C15: - | D15: % of downforce on the front axle.
A16: Downforce at 60 km/h | C16: N | D16: 0.5·ρ·V²·ClA; ρ≈1.18.
A17: Platform sensitivity | C17: - | D17: Downforce change with ride height / rake.
A19: If running no aero, leave Cl·A and Cd·A at 0 — the lap sim then treats the car as non-aero.

Sheet Brakes
A1: BRAKING — hand-off
A2: Dynamic axle loads come from VD; compute the ideal bias and return the hardware that achieves it.
A4: WHAT VD GIVES YOU (pulled live — do not edit)
A5: Parameter | B5: Value | C5: Unit | D5: Source
A6: Front axle under braking | B6: =Master!C34+LoadTransfer!C8 -> 1843.3939 | C6: N | D6: LoadTransfer
A7: Rear axle under braking | B7: =Master!C35-LoadTransfer!C8 -> 746.44606 | C7: N | D7: LoadTransfer
A8: Ideal brake bias (front) | B8: =(Master!C34+LoadTransfer!C8)/(Master!C33) -> 0.71177908 | C8: - | D8: front dynamic / total weight
A9: Target decel | B9: =Master!C26 -> 1.5 | C9: g | D9: Master
A10: Peak μ (lock-up limit) | B10: =Master!C20 -> 1.5 | C10: - | D10: Tyre — decel cannot exceed this
A12: WHAT YOU GIVE BACK TO VD (fill these — they feed the model)
A13: Parameter | B13: Value | C13: Unit | D13: Notes
A14: Rotor effective radius | B14: 90 | C14: mm
A15: Caliper piston area | B15: 1200 | C15: mm²
A16: Pad friction μ | B16: 0.4 | C16: -
A17: MC sizes (F / R) | C17: mm | D17: Set the bias with these + bias bar.
A18: Achieved bias (front) | C18: - | D18: Match to the ideal bias above.

Sheet Ergonomics
A1: ERGONOMICS / DRIVER PACKAGE — hand-off
A2: Wheelbase and mass context come from VD; return the driver-package numbers that feed the mass budget and the cockpit.
A4: WHAT VD GIVES YOU (pulled live — do not edit)
A5: Parameter | B5: Value | C5: Unit | D5: Source
A6: Wheelbase | B6: =Master!C15 -> 1550 | C6: mm | D6: Master
A7: CoG height | B7: =Master!C11 -> 263.40909 | C7: mm | D7: Master
A8: Total mass | B8: =Master!C9 -> 264 | C8: kg | D8: Master
A10: WHAT YOU GIVE BACK TO VD (fill these — they feed the model)
A11: Parameter | B11: Value | C11: Unit | D11: Notes
A12: Driver mass (strapped) | B12: 75 | C12: kg | D12: Update the Driver row in MassBudget.
A13: Driver CoG height | B13: 300 | C13: mm | D13: Feeds CoG height via MassBudget.
A14: Seat back angle | B14: 45 | C14: deg | D14: Comfort + roll-hoop clearance.
A15: Pedal-box adjustment range | B15: 275 | C15: mm | D15: Fit 5th–95th percentile.
A16: Steering wheel reach | C16: mm
A17: Roll-hoop helmet clearance | C17: mm | D17: ≥ rule minimum.
A19: Egress target: driver out in < 5 s (practise it). Confirm 95th-percentile fit AND 5th-percentile reach to all controls.

Sheet Telemetry
A1: TELEMETRY & DRIVER — channel plan & debrief
A2: Reference the VD team hands to Telemetry. Sample rates from Book Two, Part K. Add CAN IDs as the harness is built.
A4: Channel | B4: Sensor | C4: Sample rate | D4: VD use
A5: Damper position ×4 | B5: Linear pot | C5: 200–1000 Hz | D5: Ride height, roll, pitch, damper velocity
A6: Accel x/y/z | B6: IMU | C6: 100–500 Hz | D6: Load transfer, g-g
A7: Yaw/roll/pitch rate | B7: IMU gyro | C7: 100–500 Hz | D7: Yaw response, stability
A8: Wheel speed ×4 | B8: Hall + ring | C8: 100–500 Hz | D8: Slip ratio, lock-up
A9: Steering angle | B9: Rotary | C9: 100–200 Hz | D9: Understeer gradient, Ackermann
A10: Brake pressure F/R | B10: Transducer | C10: 100–200 Hz | D10: Bias, threshold braking
A11: Throttle | B11: APPS/TPS | C11: 100–200 Hz | D11: On/off-throttle balance
A12: Pushrod load | B12: Strain gauge | C12: 200–1000 Hz | D12: True tyre load, contact-patch variation
A13: Tyre temp / pressure | B13: IR / TPMS | C13: 10–25 Hz | D13: Camber/pressure, thermal window
A14: GPS | B14: GPS | C14: 10–25 Hz | D14: Lap/segment time, track map

Sheet ECS
A1: ECS / ELECTRICAL — reference & returns
A2: Power and wiring reference. Return battery and stator numbers so the mass budget and lap sim stay correct.
A4: Item | B4: Value | C4: Unit | D4: Notes
A5: Battery | B5: 12V 9Ah | C5: - | D5: Mass feeds MassBudget
A6: Battery mass | B6: 4.0 | C6: kg | D6: Update MassBudget row
A7: Main fuse | B7: 150 | C7: A | D7: Resettable
A8: Stator output | B8: 296 | C8: W | D8: Charging budget
A9: Grounding | B9: Star at battery | C9: - | D9: Clean DAQ foundation
A10: Harness wire | B10: UL1332 PTFE | C10: - | D10: Per Book Two

Sheet DecisionMatrix
A1: WEIGHTED DECISION MATRIX (Pugh)
A2: Score each option 1–5 against the weighted criteria; the weighted total picks the defensible choice. Copy the method for any pick (tyre, damper, material) — judges love this in the design event.
A4: Criterion | B4: Weight (1–5) | C4: Option A (18×6) | D4: Option B (18×7.5) | E4: Option C (other)
A5: Peak grip | B5: 5 | C5: 4 | D5: 3 | E5: 3
A6: Load sensitivity | B6: 3 | C6: 2 | D6: 4 | E6: 3
A7: Mass / inertia | B7: 4 | C7: 4 | D7: 4 | E7: 3
A8: Data availability | B8: 4 | C8: 5 | D8: 2 | E8: 2
A9: Cost / supply | B9: 3 | C9: 3 | D9: 3 | E9: 5
A10: Weighted total | C10: =SUMPRODUCT($B5:$B9,C5:C9) -> 71 | D10: =SUMPRODUCT($B5:$B9,D5:D9) -> 60 | E10: =SUMPRODUCT($B5:$B9,E5:E9) -> 59
A12: Highest weighted total = the choice. Name the two or three criteria that decided it when you present it.

Sheet Targets
A1: TARGETS vs ACHIEVED
A2: Target pulls from the model; type the achieved/measured value. For EDR and the validation story. Note the 'better' direction per row — lower is better for mass and CoG.
A4: Metric | B4: Target | C4: Achieved | D4: Unit | E4: % of target | F4: Better
A5: Lateral acceleration | B5: =Master!C25 -> 1.5 | D5: g | E5: =IFERROR(C5/B5,"") -> 0 | F5: higher
A6: Braking deceleration | B6: =Master!C26 -> 1.5 | D6: g | E6: =IFERROR(C6/B6,"") -> 0 | F6: higher
A7: Total mass | B7: =Master!C9 -> 264 | D7: kg | E7: =IFERROR(C7/B7,"") -> 0 | F7: lower
A8: CoG height | B8: =Master!C11 -> 263.40909 | D8: mm | E8: =IFERROR(C8/B8,"") -> 0 | F8: lower
A9: Roll gradient | B9: =Master!C27 -> 1.5 | D9: deg/g | E9: =IFERROR(C9/B9,"") -> 0 | F9: target
A10: Front ride frequency | B10: =Master!C28 -> 2.8 | D10: Hz | E10: =IFERROR(C10/B10,"") -> 0 | F10: target
A11: Torsional stiffness | B11: =Chassis!B15 -> 34 | D11: N·m/deg | E11: =IFERROR(C11/B11,"") -> 0 | F11: higher

Sheet Validation
A1: MODEL VALIDATION (measured vs predicted)
A2: Predicted pulls from the model; type what you measured on the car. %error shows how well the model matches reality (Book Five, Chapter 8).
A4: Quantity | B4: Predicted | C4: Measured | D4: Unit | E4: % error
A5: Skidpad lateral g (≈ μ) | B5: =Master!C20 -> 1.5 | D5: g | E5: =IFERROR((C5-B5)/B5,"") -> -1
A6: Roll gradient | B6: =Master!C27 -> 1.5 | D6: deg/g | E6: =IFERROR((C6-B6)/B6,"") -> -1
A7: CoG height | B7: =Master!C11 -> 263.40909 | D7: mm | E7: =IFERROR((C7-B7)/B7,"") -> -1
A8: Yaw inertia | B8: =Master!C12 -> 53.384439 | D8: kg·m² | E8: =IFERROR((C8-B8)/B8,"") -> -1
A9: Understeer gradient | D9: deg/g | E9: =IFERROR((C9-B9)/B9,"")
A10: Contact-patch load variation (RMS) | D10: N | E10: =IFERROR((C10-B10)/B10,"")

Sheet Nomenclature
A1: NOMENCLATURE (for the EDR)
A2: Standard symbols used across the handbook and this workbook.
A4: Symbol | B4: Quantity | C4: Unit
A5: m | B5: Vehicle mass | C5: kg
A6: W | B6: Weight | C6: N
A7: h_cg | B7: CoG height | C7: mm
A8: L | B8: Wheelbase | C8: mm
A9: t | B9: Track | C9: mm
A10: Izz | B10: Yaw moment of inertia | C10: kg·m²
A11: ay/ax | B11: Lateral / longitudinal accel | C11: g
A12: ΔFz | B12: Load transfer | C12: N
A13: μy | B13: Peak lateral friction coeff | C13: -
A14: Cα | B14: Cornering stiffness | C14: N/deg
A15: α | B15: Slip angle | C15: deg
... A29: FoS | B29: Factor of safety | C29: -

Sheet Units
A1: UNITS & CONVERSIONS
A2: Reference factors + a live converter. Type a value and pick a factor; the result computes.
A4: From | B4: To | C4: Multiply by
A5: mm | B5: in | C5: 0.03937
A6: kg | B6: lb | C6: 2.20462
A7: N | B7: kgf | C7: 0.101972
A8: kPa | B8: psi | C8: 0.145038
A9: N·m | B9: lb·ft | C9: 0.737562
A10: km/h | B10: m/s | C10: 0.277778
A11: deg | B11: rad | C11: 0.017453
A12: hp | B12: kW | C12: 0.7457
A14: LIVE CONVERTER
A15: Value | B15: 100
A16: × factor (copy from above) | B16: 2.20462
A17: Result = | B17: =B15*B16 -> 220.462

Sheet Setup
A1: CORNER SETUP SHEET (copy per run)
A2: Baseline comes from the Tyre and Springs sheets; type the run values in the four corner columns. Record date, track, temps, fuel, driver, tyre heat-cycles and the ONE change vs last run.
A4: Parameter | B4: Front L | C4: Front R | D4: Rear L | E4: Rear R
A5: Cold pressure (kPa) | B5: 69 | C5: 69 | D5: 69 | E5: 69
A6: Hot pressure (kPa)
A7: Camber (deg) | B7: -2 | C7: -2 | D7: -1.5 | E7: -1.5
A8: Toe (deg)
A9: Caster (deg)
A10: Spring rate (N/mm) | B10: 40 | C10: 40 | D10: 45 | E10: 45
A11: Ride height (mm) | B11: 40 | C11: 40 | D11: 40 | E11: 40
A12: ARB setting
A13: Damper bump
A14: Damper rebound
A15: Corner weight (N)
A17: Date
A18: Track
A19: Ambient / track temp
A20: Fuel
A21: Driver
A22: Tyre set / heat cycles
A23: ONE change vs last run
A24: Result (measured + felt)

Sheet TestLog
A1: TEST LOG
A2: One row per run. Change ONE thing at a time; record what you measured and what you felt, and the next action.
A4: Run # | B4: Date | C4: Test | D4: Setup change | E4: Measured result | F4: Next action
A5: 1 | B5: 2026-06-01 | C5: Skidpad | D5: Baseline | E5: 1.42 g; mild mid-understeer | F5: Soften front ARB one step

Sheet Procurement
A1: PROCUREMENT TRACKER
A2: Order-by date is set by lead time; flag long-lead items (dampers, bearings, tyres) early. Add Bangladesh/FSCC import + customs margin.
A4: Item | B4: Spec | C4: Supplier | D4: Quote | E4: Lead time | F4: Order-by | G4: Status | H4: Owner
A5: Dampers | B5: MTB/kart, adj. | C5: — | D5: — | E5: 8–12 wk | F5: 2026-02-01 | G5: To order | H5: VD

Sheet Gates
A1: DECISION GATES (G0–G9)
A2: Do not carry an open problem across a gate. Mark each Done when its exit criteria are met and signed.
A4: Gate | B4: You may not proceed until… | C4: Status | D4: Date / sign-off
A5: G0 Targets | B5: Rules extracted; targets set; lock-list filled & signed
A6: G1 Tyre | B6: Tyre chosen with data; validated model; operating metrics in Master
A7: G2 Concept | B7: Vehicle targets frozen (WB, track, mass, CoG, freqs, architecture)
A8: G3 Hardpoints | B8: All kinematic targets met; travel/clearances OK; coords FROZEN
A9: G4 Design | B9: Parts pass FEA; DFM/FMEA done; drawings & BOM released; long-lead ordered
A10: G5 Rates | B10: Springs/ARB/dampers sized & ordered (with a spring range)
A11: G6 Rolling chassis | B11: Built to spec; QC passed (hardpoints verified); DAQ live
A12: G7 Runner | B12: Reliable runs; car measured; baseline setup documented
A13: G8 Performance | B13: Targets met; model correlated; endurance-distance run clean
A14: G9 Competition | B14: Scrutineering self-check passed; setups/spares/drivers ready

Sheet ChangeLog
A1: CHANGE LOG
A2: Every change to a frozen number after its gate is logged here — who, what, old→new, and why.
A4: Date | B4: Sheet | C4: Parameter | D4: Old | E4: New | F4: Who | G4: Why
A5: 2026-10-08 | B5: Master | C5: CoG height | D5: 295 | E5: 290 | F5: VD | G5: Tilt-test result

Sheet ChartData
O1: 1.3
A3: t_deg | B3: Lateral g | C3: Longitudinal g | E3: Slip(deg) | F3: 250 | G3: 500 | H3: 750 | I3: 1000 | J3: 1250 | L3: Corner | M3: Load (N)
A4: 0 | B4: =Master!$C$20*SIN(RADIANS(A4)) -> 0 | C4: =Master!$C$20*COS(RADIANS(A4)) -> 1.5 | E4: -12 | F4: =Master!$C$20*F$3*SIN($O$1*ATAN((Master!$C$21/($O$1*Master!$C$20*F$3))*$E4)) -> -341.90969 | G4: =Master!$C$20*G$3*SIN($O$1*ATAN((Master!$C$21/($O$1*Master!$C$20*G$3))*$E4)) -> -697.77347 | H4: =Master!$C$20*H$3*SIN($O$1*ATAN((Master!$C$21/($O$1*Master!$C$20*H$3))*$E4)) -> -1065.1007 | I4: =Master!$C$20*I$3*SIN($O$1*ATAN((Master!$C$21/($O$1*Master!$C$20*I$3))*$E4)) -> -1441.3456 | J4: =Master!$C$20*J$3*SIN($O$1*ATAN((Master!$C$21/($O$1*Master!$C$20*J$3))*$E4)) -> -1823.9626 | L4: Outer front | M4: =LoadTransfer!C11 -> 1038.7543
A5: 10 | B5: =Master!$C$20*SIN(RADIANS(A5)) -> 0.26047227 | C5: =Master!$C$20*COS(RADIANS(A5)) -> 1.4772116 | E5: -11 | F5: =Master!$C$20*F$3*SIN($O$1*ATAN((Master!$C$21/($O$1*Master!$C$20*F$3))*$E5)) -> -342.57769 | G5: =Master!$C$20*G$3*SIN($O$1*ATAN((Master!$C$21/($O$1*Master!$C$20*G$3))*$E5)) -> -700.13329 | H5: =Master!$C$20*H$3*SIN($O$1*ATAN((Master!$C$21/($O$1*Master!$C$20*H$3))*$E5)) -> -1069.6915 | I5: =Master!$C$20*I$3*SIN($O$1*ATAN((Master!$C$21/($O$1*Master!$C$20*I$3))*$E5)) -> -1448.2183 | J5: =Master!$C$20*J$3*SIN($O$1*ATAN((Master!$C$21/($O$1*Master!$C$20*J$3))*$E5)) -> -1832.6995 | L5: Inner front | M5: =LoadTransfer!C12 -> 144.45825
A6: 20 | B6: =Master!$C$20*SIN(RADIANS(A6)) -> 0.51303021 | C6: =Master!$C$20*COS(RADIANS(A6)) -> 1.4095389 | E6: -10 | F6: =Master!$C$20*F$3*SIN($O$1*ATAN((Master!$C$21/($O$1*Master!$C$20*F$3))*$E6)) -> -343.37047 | G6: =Master!$C$20*G$3*SIN($O$1*ATAN((Master!$C$21/($O$1*Master!$C$20*G$3))*$E6)) -> -702.89224 | H6: =Master!$C$20*H$3*SIN($O$1*ATAN((Master!$C$21/($O$1*Master!$C$20*H$3))*$E6)) -> -1074.9509 | I6: =Master!$C$20*I$3*SIN($O$1*ATAN((Master!$C$21/($O$1*Master!$C$20*I$3))*$E6)) -> -1455.8752 | J6: =Master!$C$20*J$3*SIN($O$1*ATAN((Master!$C$21/($O$1*Master!$C$20*J$3))*$E6)) -> -1842.0495 | L6: Outer rear | M6: =LoadTransfer!C13 -> 1116.0658
A7: 30 | B7: =Master!$C$20*SIN(RADIANS(A7)) -> 0.75 | C7: =Master!$C$20*COS(RADIANS(A7)) -> 1.2990381 | E7: -9 | F7: =Master!$C$20*F$3*SIN($O$1*ATAN((Master!$C$21/($O$1*Master!$C$20*F$3))*$E7)) -> -344.3263 | G7: =Master!$C$20*G$3*SIN($O$1*ATAN((Master!$C$21/($O$1*Master!$C$20*G$3))*$E7)) -> -706.15592 | H7: =Master!$C$20*H$3*SIN($O$1*ATAN((Master!$C$21/($O$1*Master!$C$20*H$3))*$E7)) -> -1081.0092 | I7: =Master!$C$20*I$3*SIN($O$1*ATAN((Master!$C$21/($O$1*Master!$C$20*I$3))*$E7)) -> -1464.3633 | J7: =Master!$C$20*J$3*SIN($O$1*ATAN((Master!$C$21/($O$1*Master!$C$20*J$3))*$E7)) -> -1851.82 | L7: Inner rear | M7: =LoadTransfer!C14 -> 290.56167
A8: 40 | B8: =Master!$C$20*SIN(RADIANS(A8)) -> 0.96418141 | C8: =Master!$C$20*COS(RADIANS(A8)) -> 1.1490667 | E8: -8 | F8: =Master!$C$20*F$3*SIN($O$1*ATAN((Master!$C$21/($O$1*Master!$C$20*F$3))*$E8)) -> -345.50068 | G8: =Master!$C$20*G$3*SIN($O$1*ATAN((Master!$C$21/($O$1*Master!$C$20*G$3))*$E8)) -> -710.06716 | H8: =Master!$C$20*H$3*SIN($O$1*ATAN((Master!$C$21/($O$1*Master!$C$20*H$3))*$E8)) -> -1088.0101 | I8: =Master!$C$20*I$3*SIN($O$1*ATAN((Master!$C$21/($O$1*Master!$C$20*I$3))*$E8)) -> -1473.6396 | J8: =Master!$C$20*J$3*SIN($O$1*ATAN((Master!$C$21/($O$1*Master!$C$20*J$3))*$E8)) -> -1861.525
A9: 50 | B9: =Master!$C$20*SIN(RADIANS(A9)) -> 1.1490667 | C9: =Master!$C$20*COS(RADIANS(A9)) -> 0.96418141 | E9: -7 | F9: =Master!$C$20*F$3*SIN($O$1*ATAN((Master!$C$21/($O$1*Master!$C$20*F$3))*$E9)) -> -346.97712 | G9: =Master!$C$20*G$3*SIN($O$1*ATAN((Master!$C$21/($O$1*Master!$C$20*G$3))*$E9)) -> -714.81995 | H9: =Master!$C$20*H$3*SIN($O$1*ATAN((Master!$C$21/($O$1*Master!$C$20*H$3))*$E9)) -> -1096.081 | I9: =Master!$C$20*I$3*SIN($O$1*ATAN((Master!$C$21/($O$1*Master!$C$20*I$3))*$E9)) -> -1483.4252 | J9: =Master!$C$20*J$3*SIN($O$1*ATAN((Master!$C$21/($O$1*Master!$C$20*J$3))*$E9)) -> -1870.0489
A10: 60 | B10: =Master!$C$20*SIN(RADIANS(A10)) -> 1.2990381 | C10: =Master!$C$20*COS(RADIANS(A10)) -> 0.75 | E10: -6 | F10: =Master!$C$20*F$3*SIN($O$1*ATAN((Master!$C$21/($O$1*Master!$C$20*F$3))*$E10)) -> -348.88673 | G10: =Master!$C$20*G$3*SIN($O$1*ATAN((Master!$C$21/($O$1*Master!$C$20*G$3))*$E10)) -> -720.67281 | H10: =Master!$C$20*H$3*SIN($O$1*ATAN((Master!$C$21/($O$1*Master!$C$20*H$3))*$E10)) -> -1105.2297 | I10: =Master!$C$20*I$3*SIN($O$1*ATAN((Master!$C$21/($O$1*Master!$C$20*I$3))*$E10)) -> -1492.836 | J10: =Master!$C$20*J$3*SIN($O$1*ATAN((Master!$C$21/($O$1*Master!$C$20*J$3))*$E10)) -> -1874.8798
A11: 70 | B11: =Master!$C$20*SIN(RADIANS(A11)) -> 1.4095389 | C11: =Master!$C$20*COS(RADIANS(A11)) -> 0.51303021 | E11: -5 | F11: =Master!$C$20*F$3*SIN($O$1*ATAN((Master!$C$21/($O$1*Master!$C$20*F$3))*$E11)) -> -351.44612 | G11: =Master!$C$20*G$3*SIN($O$1*ATAN((Master!$C$21/($O$1*Master!$C$20*G$3))*$E11)) -> -727.93759 | H11: =Master!$C$20*H$3*SIN($O$1*ATAN((Master!$C$21/($O$1*Master!$C$20*H$3))*$E11)) -> -1115.0085 | I11: =Master!$C$20*I$3*SIN($O$1*ATAN((Master!$C$21/($O$1*Master!$C$20*I$3))*$E11)) -> -1499.3992 | J11: =Master!$C$20*J$3*SIN($O$1*ATAN((Master!$C$21/($O$1*Master!$C$20*J$3))*$E11)) -> -1870.2652
A12: 80 | B12: =Master!$C$20*SIN(RADIANS(A12)) -> 1.4772116 | C12: =Master!$C$20*COS(RADIANS(A12)) -> 0.26047227 | E12: -4 | F12: =Master!$C$20*F$3*SIN($O$1*ATAN((Master!$C$21/($O$1*Master!$C$20*F$3))*$E12)) -> -355.03358 | G12: =Master!$C$20*G$3*SIN($O$1*ATAN((Master!$C$21/($O$1*Master!$C$20*G$3))*$E12)) -> -736.81981 | H12: =Master!$C$20*H$3*SIN($O$1*ATAN((Master!$C$21/($O$1*Master!$C$20*H$3))*$E12)) -> -1123.3558 | I12: =Master!$C$20*I$3*SIN($O$1*ATAN((Master!$C$21/($O$1*Master!$C$20*I$3))*$E12)) -> -1496.2122 | J12: =Master!$C$20*J$3*SIN($O$1*ATAN((Master!$C$21/($O$1*Master!$C$20*J$3))*$E12)) -> -1842.5138
A13: 90 | B13: =Master!$C$20*SIN(RADIANS(A13)) -> 1.5 | C13: =Master!$C$20*COS(RADIANS(A13)) -> 9.184851e-17 | E13: -3 | F13: =Master!$C$20*F$3*SIN($O$1*ATAN((Master!$C$21/($O$1*Master!$C$20*F$3))*$E13)) -> -360.3364 | G13: =Master!$C$20*G$3*SIN($O$1*ATAN((Master!$C$21/($O$1*Master!$C$20*G$3))*$E13)) -> -746.41802 | H13: =Master!$C$20*H$3*SIN($O$1*ATAN((Master!$C$21/($O$1*Master!$C$20*H$3))*$E13)) -> -1122.1591 | I13: =Master!$C$20*I$3*SIN($O$1*ATAN((Master!$C$21/($O$1*Master!$C$20*I$3))*$E13)) -> -1462.9962 | J13: =Master!$C$20*J$3*SIN($O$1*ATAN((Master!$C$21/($O$1*Master!$C$20*J$3))*$E13)) -> -1757.5611
A14: 100 | B14: =Master!$C$20*SIN(RADIANS(A14)) -> 1.4772116 | C14: =Master!$C$20*COS(RADIANS(A14)) -> -0.26047227 | E14: -2 | F14: =Master!$C$20*F$3*SIN($O$1*ATAN((Master!$C$21/($O$1*Master!$C$20*F$3))*$E14)) -> -368.4099 | G14: =Master!$C$20*G$3*SIN($O$1*ATAN((Master!$C$21/($O$1*Master!$C$20*G$3))*$E14)) -> -748.10608 | H14: =Master!$C$20*H$3*SIN($O$1*ATAN((Master!$C$21/($O$1*Master!$C$20*H$3))*$E14)) -> -1077.554 | I14: =Master!$C$20*I$3*SIN($O$1*ATAN((Master!$C$21/($O$1*Master!$C$20*I$3))*$E14)) -> -1336.2911 | J14: =Master!$C$20*J$3*SIN($O$1*ATAN((Master!$C$21/($O$1*Master!$C$20*J$3))*$E14)) -> -1530.0454
A15: 110 | B15: =Master!$C$20*SIN(RADIANS(A15)) -> 1.4095389 | C15: =Master!$C$20*COS(RADIANS(A15)) -> -0.51303021 | E15: -1 | F15: =Master!$C$20*F$3*SIN($O$1*ATAN((Master!$C$21/($O$1*Master!$C$20*F$3))*$E15)) -> -374.05304 | G15: =Master!$C$20*G$3*SIN($O$1*ATAN((Master!$C$21/($O$1*Master!$C$20*G$3))*$E15)) -> -668.14553 | H15: =Master!$C$20*H$3*SIN($O$1*ATAN((Master!$C$21/($O$1*Master!$C$20*H$3))*$E15)) -> -836.46639 | I15: =Master!$C$20*I$3*SIN($O$1*ATAN((Master!$C$21/($O$1*Master!$C$20*I$3))*$E15)) -> -928.75797 | J15: =Master!$C$20*J$3*SIN($O$1*ATAN((Master!$C$21/($O$1*Master!$C$20*J$3))*$E15)) -> -981.78901
A16: 120 | B16: =Master!$C$20*SIN(RADIANS(A16)) -> 1.2990381 | C16: =Master!$C$20*COS(RADIANS(A16)) -> -0.75 | E16: 0 | F16: =Master!$C$20*F$3*SIN($O$1*ATAN((Master!$C$21/($O$1*Master!$C$20*F$3))*$E16)) -> 0 | G16: =Master!$C$20*G$3*SIN($O$1*ATAN((Master!$C$21/($O$1*Master!$C$20*G$3))*$E16)) -> 0 | H16: =Master!$C$20*H$3*SIN($O$1*ATAN((Master!$C$21/($O$1*Master!$C$20*H$3))*$E16)) -> 0 | I16: =Master!$C$20*I$3*SIN($O$1*ATAN((Master!$C$21/($O$1*Master!$C$20*I$3))*$E16)) -> 0 | J16: =Master!$C$20*J$3*SIN($O$1*ATAN((Master!$C$21/($O$1*Master!$C$20*J$3))*$E16)) -> 0
A17: 130 | B17: =Master!$C$20*SIN(RADIANS(A17)) -> 1.1490667 | C17: =Master!$C$20*COS(RADIANS(A17)) -> -0.96418141 | E17: 1 | F17: =Master!$C$20*F$3*SIN($O$1*ATAN((Master!$C$21/($O$1*Master!$C$20*F$3))*$E17)) -> 374.05304 | G17: =Master!$C$20*G$3*SIN($O$1*ATAN((Master!$C$21/($O$1*Master!$C$20*G$3))*$E17)) -> 668.14553 | H17: =Master!$C$20*H$3*SIN($O$1*ATAN((Master!$C$21/($O$1*Master!$C$20*H$3))*$E17)) -> 836.46639 | I17: =Master!$C$20*I$3*SIN($O$1*ATAN((Master!$C$21/($O$1*Master!$C$20*I$3))*$E17)) -> 928.75797 | J17: =Master!$C$20*J$3*SIN($O$1*ATAN((Master!$C$21/($O$1*Master!$C$20*J$3))*$E17)) -> 981.78901
A18: 140 | B18: =Master!$C$20*SIN(RADIANS(A18)) -> 0.96418141 | C18: =Master!$C$20*COS(RADIANS(A18)) -> -1.1490667 | E18: 2 | F18: =Master!$C$20*F$3*SIN($O$1*ATAN((Master!$C$21/($O$1*Master!$C$20*F$3))*$E18)) -> 368.4099 | G18: =Master!$C$20*G$3*SIN($O$1*ATAN((Master!$C$21/($O$1*Master!$C$20*G$3))*$E18)) -> 748.10608 | H18: =Master!$C$20*H$3*SIN($O$1*ATAN((Master!$C$21/($O$1*Master!$C$20*H$3))*$E18)) -> 1077.554 | I18: =Master!$C$20*I$3*SIN($O$1*ATAN((Master!$C$21/($O$1*Master!$C$20*I$3))*$E18)) -> 1336.2911 | J18: =Master!$C$20*J$3*SIN($O$1*ATAN((Master!$C$21/($O$1*Master!$C$20*J$3))*$E18)) -> 1530.0454
A19: 150 | B19: =Master!$C$20*SIN(RADIANS(A19)) -> 0.75 | C19: =Master!$C$20*COS(RADIANS(A19)) -> -1.2990381 | E19: 3 | F19: =Master!$C$20*F$3*SIN($O$1*ATAN((Master!$C$21/($O$1*Master!$C$20*F$3))*$E19)) -> 360.3364 | G19: =Master!$C$20*G$3*SIN($O$1*ATAN((Master!$C$21/($O$1*Master!$C$20*G$3))*$E19)) -> 746.41802 | H19: =Master!$C$20*H$3*SIN($O$1*ATAN((Master!$C$21/($O$1*Master!$C$20*H$3))*$E19)) -> 1122.1591 | I19: =Master!$C$20*I$3*SIN($O$1*ATAN((Master!$C$21/($O$1*Master!$C$20*I$3))*$E19)) -> 1462.9962 | J19: =Master!$C$20*J$3*SIN($O$1*ATAN((Master!$C$21/($O$1*Master!$C$20*J$3))*$E19)) -> 1757.5611
... A28: 240 | B28: =Master!$C$20*SIN(RADIANS(A28)) -> -1.2990381 | C28: =Master!$C$20*COS(RADIANS(A28)) -> -0.75 | E28: 12 | F28: =Master!$C$20*F$3*SIN($O$1*ATAN((Master!$C$21/($O$1*Master!$C$20*F$3))*$E28)) -> 341.90969 | G28: =Master!$C$20*G$3*SIN($O$1*ATAN((Master!$C$21/($O$1*Master!$C$20*G$3))*$E28)) -> 697.77347 | H28: =Master!$C$20*H$3*SIN($O$1*ATAN((Master!$C$21/($O$1*Master!$C$20*H$3))*$E28)) -> 1065.1007 | I28: =Master!$C$20*I$3*SIN($O$1*ATAN((Master!$C$21/($O$1*Master!$C$20*I$3))*$E28)) -> 1441.3456 | J28: =Master!$C$20*J$3*SIN($O$1*ATAN((Master!$C$21/($O$1*Master!$C$20*J$3))*$E28)) -> 1823.9626
A29: 250 | B29: =Master!$C$20*SIN(RADIANS(A29)) -> -1.4095389 | C29: =Master!$C$20*COS(RADIANS(A29)) -> -0.51303021
A30: 260 | B30: =Master!$C$20*SIN(RADIANS(A30)) -> -1.4772116 | C30: =Master!$C$20*COS(RADIANS(A30)) -> -0.26047227
A31: 270 | B31: =Master!$C$20*SIN(RADIANS(A31)) -> -1.5 | C31: =Master!$C$20*COS(RADIANS(A31)) -> -2.7554553e-16
A32: 280 | B32: =Master!$C$20*SIN(RADIANS(A32)) -> -1.4772116 | C32: =Master!$C$20*COS(RADIANS(A32)) -> 0.26047227
A33: 290 | B33: =Master!$C$20*SIN(RADIANS(A33)) -> -1.4095389 | C33: =Master!$C$20*COS(RADIANS(A33)) -> 0.51303021
A34: 300 | B34: =Master!$C$20*SIN(RADIANS(A34)) -> -1.2990381 | C34: =Master!$C$20*COS(RADIANS(A34)) -> 0.75
A35: 310 | B35: =Master!$C$20*SIN(RADIANS(A35)) -> -1.1490667 | C35: =Master!$C$20*COS(RADIANS(A35)) -> 0.96418141
A36: 320 | B36: =Master!$C$20*SIN(RADIANS(A36)) -> -0.96418141 | C36: =Master!$C$20*COS(RADIANS(A36)) -> 1.1490667
A37: 330 | B37: =Master!$C$20*SIN(RADIANS(A37)) -> -0.75 | C37: =Master!$C$20*COS(RADIANS(A37)) -> 1.2990381
A38: 340 | B38: =Master!$C$20*SIN(RADIANS(A38)) -> -0.51303021 | C38: =Master!$C$20*COS(RADIANS(A38)) -> 1.4095389
A39: 350 | B39: =Master!$C$20*SIN(RADIANS(A39)) -> -0.26047227 | C39: =Master!$C$20*COS(RADIANS(A39)) -> 1.4772116
A40: 360 | B40: =Master!$C$20*SIN(RADIANS(A40)) -> -3.6739404e-16 | C40: =Master!$C$20*COS(RADIANS(A40)) -> 1.5
